isbnlib_worldcat/__init__.py
isbnlib_worldcat/_worldcat.py
isbnlib_worldcat2-0.1.2.dist-info/LICENSE
isbnlib_worldcat2-0.1.2.dist-info/METADATA
isbnlib_worldcat2-0.1.2.dist-info/WHEEL
isbnlib_worldcat2-0.1.2.dist-info/entry_points.txt
isbnlib_worldcat2-0.1.2.dist-info/top_level.txt
isbnlib_worldcat2-0.1.2.dist-info/RECORD
