Metadata-Version: 2.1
Name: isbnlib-worldcat2
Version: 0.1.2
Summary: An isbnlib plugin for the WorldCat service (https://www.worldcat.org/).
Home-page: https://github.com/pwssnk/isbnlib-worldcat
Author: pwssnk
Author-email: UNKNOWN
License: LGPL v3
Keywords: ISBN,isbnlib,WorldCat
Platform: UNKNOWN
Classifier: Programming Language :: Python
Classifier: Programming Language :: Python :: 3
Classifier: Programming Language :: Python :: 3.5
Classifier: Programming Language :: Python :: 3.6
Classifier: Programming Language :: Python :: 3.7
Classifier: License :: OSI Approved :: GNU Lesser General Public License v3 (LGPLv3)
Classifier: Operating System :: OS Independent
Classifier: Development Status :: 3 - Alpha
Classifier: Intended Audience :: Developers
Classifier: Intended Audience :: End Users/Desktop
Classifier: Environment :: Console
Classifier: Topic :: Text Processing :: General
Classifier: Topic :: Software Development :: Libraries :: Python Modules
Requires-Dist: isbnlib (>=3.9.1)
Requires-Dist: pycountry (>=1.12.8)
Requires-Dist: beautifulsoup4 (>=4.7.1)
